modernqt/__init__.py
modernqt/src/core/__init__.py
modernqt/src/core/dialog.py
modernqt/src/core/exceptions.py
modernqt/src/core/font.py
modernqt/src/core/load.py
modernqt/src/ui/angle-down.png
modernqt/src/ui/angle-down.svg
modernqt/widgets/__init__.py
modernqt/widgets/basic/button.py
modernqt/widgets/basic/groups.py
modernqt/widgets/basic/label.py
modernqt/widgets/basic/styles/button.css
modernqt/widgets/basic/styles/check_box.css
modernqt/widgets/basic/styles/digital_entry.css
modernqt/widgets/basic/styles/drop_down_menu.css
modernqt/widgets/basic/styles/entry.css
modernqt/widgets/basic/styles/group_box.css
modernqt/widgets/basic/styles/radio_button.css
modernqt/widgets/basic/styles/widgets_list.css
modernqt/widgets/basic/switchers.py
modernqt/widgets/basic/widgets_list.py
modernqt-0.1.0.dist-info/LICENSE
modernqt-0.1.0.dist-info/METADATA
modernqt-0.1.0.dist-info/WHEEL
modernqt-0.1.0.dist-info/RECORD
