Metadata-Version: 2.1
Name: modernqt
Version: 0.1.0
Summary: 
License: MIT
Author: chebupelka8
Author-email: stpzamyatin@gmail.com
Requires-Python: >=3.11,<3.13
Classifier: License :: OSI Approved :: MIT License
Classifier: Programming Language :: Python :: 3
Classifier: Programming Language :: Python :: 3.11
Classifier: Programming Language :: Python :: 3.12
